lektor_asciidoctor.py
lektor_asciidoctor-0.1.dist-info/METADATA
lektor_asciidoctor-0.1.dist-info/RECORD
lektor_asciidoctor-0.1.dist-info/WHEEL
lektor_asciidoctor-0.1.dist-info/entry_points.txt
lektor_asciidoctor-0.1.dist-info/top_level.txt
