Metadata-Version: 2.1
Name: lektor-asciidoctor
Version: 0.1
Summary: Adds AsciiDoc field type to Lektor.
Home-page: https://github.com/andresperezcera/lektor-asciidoctor.git
Author: Andres Perez C.
Author-email: andresperezcera@gmail.com
License: MIT
Keywords: Lektor plugin static-site blog asciidoc,using Asciidoctor Ruby Gem
Platform: UNKNOWN
Classifier: Environment :: Plugins
Classifier: Environment :: Web Environment
Classifier: Framework :: Lektor
Classifier: Intended Audience :: Developers
Classifier: License :: OSI Approved :: MIT License
